advthumbnailer.py
pelican_advthumbnailer-1.0.0.dist-info/LICENSE
pelican_advthumbnailer-1.0.0.dist-info/METADATA
pelican_advthumbnailer-1.0.0.dist-info/WHEEL
pelican_advthumbnailer-1.0.0.dist-info/top_level.txt
pelican_advthumbnailer-1.0.0.dist-info/RECORD
