Metadata-Version: 2.1
Name: pelican-advthumbnailer
Version: 1.0.0
Summary: A thumbnail generator for Pelican that operates by looking at the filename of missing files to determine thumb format.
Home-page: https://github.com/AlexJF/pelican-advthumbnailer
Download-URL: https://github.com/AlexJF/pelican-advthumbnailer/archive/v1.0.0.zip
Author: Alexandre Fonseca
Author-email: alexandrejorgefonseca@gmail.com
License: Apache
Keywords: pelican blog static thumbnail generation
Platform: UNKNOWN
License-File: LICENSE
Requires-Dist: pelican (>=3.4.0)
Requires-Dist: beautifulsoup4 (>=4.3.2)
Requires-Dist: Pillow (>=2.5.3)
